threadxpools/__init__.py
threadxpools/main.py
threadxpools-1.3.dist-info/METADATA
threadxpools-1.3.dist-info/WHEEL
threadxpools-1.3.dist-info/top_level.txt
threadxpools-1.3.dist-info/RECORD
